Workbook

Sheet Inputs
A1: Next Step Middle East — Acronis quote model
A2: Price list: Acronis Cyber Cloud Calculator C26.09 (USD). Buy prices are Acronis list to partner, USD per unit per month.
A4: Legend
A5: Blue text on yellow = key inputs to set for every quote
A6: Blue text = inputs and assumptions you may change
A7: Black = formulas. Do not overwrite.
A9: Quote settings
A10: Customer name | B10: Example Trading Co. (illustrative)
A11: Proposal reference | B11: NS-ACR-2026-001
A12: Proposal date | B12: 2026-10-01
A13: Currency code | B13: SAR
A14: FX rate: local currency per 1 USD | B14: 3.75
A15: VAT rate | B15: 0.15
A16: Next Step commitment tier (USD per month) | B16: 1000
A17: Contract term (months) | B17: 12
A18: Validity (days) | B18: 90
A19: Rounding of unit sell price (decimals) | B19: 2
A21: Margin assumptions by SKU family (gross margin on Acronis buy price)
A22: These defaults are placeholders pending the Next Step margin policy decision (decisions-log.md, 2026-10-01). Change them here; every quote line uses them unless overridden.
A23: Margin family | B23: Default margin % | C23: Covers
A24: Bundles | B24: 0.35 | C24: Solution-based bundles: Security + RMM, Backup + DR, Ultimate Protection and their add-ons
A25: Security | B25: 0.4 | C25: EDR, XDR, MDR, email and collaboration security, awareness training, DLP, GenAI Protection
A26: Backup & DR | B26: 0.35 | C26: Per-workload backup, disaster recovery, email archiving, files sync and share
A27: Storage | B27: 0.25 | C27: Per-GB storage, geo-redundancy, compute points, public IPs
A28: Operations | B28: 0.3 | C28: RMM and PSA
A29: Infrastructure | B29: 0.2 | C29: Cyber Frame, Cyber Infrastructure, Cyber Workspace
A30: Other | B30: 0.1 | C30: Pass-through services such as physical data shipping
A32: Service fees (local currency)
A33: Managed service fee per protected workload per month | B33: 15
A34: Fixed managed service fee per month | B34: 0
A35: Onboarding and migration (one-time) | B35: 7500
A36: DR runbook and first failover test (one-time) | B36: 0
A37: Training (one-time) | B37: 0
A39: Notes
A40: 1. Buy prices come from the Pricelist sheet (C26.09 USD). Replace that sheet when Acronis publishes a new list.
A41: 2. Unit sell (USD) = unit buy / (1 - margin). Unit sell (local) = unit sell (USD) x FX rate, rounded.
A42: 3. Storage-bearing SKUs exist in G1 and G2 variants; choose the SKU that matches the data center in the proposal.
A43: 4. The Tier analysis sheet shows this quote's buy cost at every commitment tier.
A44: 5. Nothing in this workbook is customer-facing except the Summary sheet.

Sheet Pricelist
A1: Acronis price list — partner buy prices, USD per unit per month
A2: Source: Acronis Cyber Cloud Calculator C26.09 (USD). Column O picks the price for the tier chosen in Inputs!B16.
A3: Licensing group | B3: Category | C3: DC group | D3: SKU code | E3: SKU name | F3: Margin family | G3: Tier 250 | H3: Tier 500 | I3: Tier 1,000 | J3: Tier 2,000 | K3: Tier 4,000 | L3: Tier 7,000 | M3: Tier 10,000 | N3: Tier 15,000 | O3: Price at selected tier
F4: Commitment USD/month → | G4: 250 | H4: 500 | I4: 1000 | J4: 2000 | K4: 4000 | L4: 7000 | M4: 10000 | N4: 15000
A5: Solution-based licensing | B5: Security + RMM | C5: All | D5: SESDMSENS | E5: Security + RMM - WL - Endpoint - Acronis Cyber Protect Cloud | F5: Bundles | G5: 2.8 | H5: 2.6 | I5: 2.29 | J5: 1.99 | K5: 1.65 | L5: 1.58 | M5: 1.5 | N5: 1.47 | O5: =INDEX($G5:$N5,1,MATCH(Inputs!$B$16,$G$4:$N$4,0)) -> 2.29
A6: Solution-based licensing | B6: Security + RMM | C6: All | D6: SESEMSENS | E6: Security + RMM - WL - Microsoft 365 seat - Acronis Cyber Protect Cloud | F6: Bundles | G6: 3.2 | H6: 3.1 | I6: 3.01 | J6: 2.86 | K6: 2.72 | L6: 2.61 | M6: 2.51 | N6: 2.46 | O6: =INDEX($G6:$N6,1,MATCH(Inputs!$B$16,$G$4:$N$4,0)) -> 3.01
A7: Solution-based licensing | B7: Security + RMM | C7: All | D7: SESFMSENS | E7: Security + RMM - WL - Google Workspace seat - Acronis Cyber Protect Cloud | F7: Bundles | G7: 2.4 | H7: 2.33 | I7: 2.26 | J7: 2.15 | K7: 2.04 | L7: 1.96 | M7: 1.88 | N7: 1.84 | O7: =INDEX($G7:$N7,1,MATCH(Inputs!$B$16,$G$4:$N$4,0)) -> 2.26
A8: Solution-based licensing | B8: Backup and Disaster Recovery | C8: G1 | D8: SBDAMSENS | E8: BDR - WL - Server (3 TB of Acronis Hosted Storage included) - G1 - Acronis Cyber Protect Cloud | F8: Bundles | G8: 65 | H8: 60.45 | I8: 55.61 | J8: 50.05 | K8: 46.05 | L8: 44.21 | M8: 42 | N8: 41.16 | O8: =INDEX($G8:$N8,1,MATCH(Inputs!$B$16,$G$4:$N$4,0)) -> 55.61
A9: Solution-based licensing | B9: Backup and Disaster Recovery | C9: G1 | D9: SBDBMSENS | E9: BDR - WL - VM (2 TB of Acronis Hosted Storage included) - G1 - Acronis Cyber Protect Cloud | F9: Bundles | G9: 45 | H9: 41.85 | I9: 38.5 | J9: 34.65 | K9: 31.88 | L9: 30.6 | M9: 29.07 | N9: 28.49 | O9: =INDEX($G9:$N9,1,MATCH(Inputs!$B$16,$G$4:$N$4,0)) -> 38.5
A10: Solution-based licensing | B10: Backup and Disaster Recovery | C10: G1 | D10: SBDCMSENS | E10: BDR - WL - Workstation (300 GB of Acronis Hosted Storage included) - G1 - Acronis Cyber Protect Cloud | F10: Bundles | G10: 9 | H10: 8.37 | I10: 7.7 | J10: 6.55 | K10: 5.9 | L10: 5.55 | M10: 5.11 | N10: 5.01 | O10: =INDEX($G10:$N10,1,MATCH(Inputs!$B$16,$G$4:$N$4,0)) -> 7.7
A11: Solution-based licensing | B11: Backup and Disaster Recovery | C11: G1 | D11: SBDDMSENS | E11: BDR - WL - Microsoft 365 seat (unlimited Acronis Hosted Cloud Storage included1) - G1 - Acronis Cyber Protect Cloud | F11: Bundles | G11: 3 | H11: 2.85 | I11: 2.65 | J11: 2.39 | K11: 2.2 | L11: 2.11 | M11: 2.03 | N11: 1.99 | O11: =INDEX($G11:$N11,1,MATCH(Inputs!$B$16,$G$4:$N$4,0)) -> 2.65
A12: Solution-based licensing | B12: Backup and Disaster Recovery | C12: G1 | D12: SBDEMSENS | E12: BDR - WL - Google Workspace seat (unlimited Acronis Hosted Cloud Storage included1) - G1 - Acronis Cyber Protect Cloud | F12: Bundles | G12: 2.4 | H12: 2.28 | I12: 2.12 | J12: 1.91 | K12: 1.76 | L12: 1.69 | M12: 1.62 | N12: 1.59 | O12: =INDEX($G12:$N12,1,MATCH(Inputs!$B$16,$G$4:$N$4,0)) -> 2.12
A13: Solution-based licensing | B13: Backup and Disaster Recovery | C13: G1 | D13: SBDGMSENS | E13: BDR - WL - Mobile Backup (50 GB of Acronis Hosted Storage included) - G1 - Acronis Cyber Protect Cloud | F13: Bundles | G13: 2 | H13: 1.84 | I13: 1.69 | J13: 1.4 | K13: 1.19 | L13: 1.14 | M13: 1.09 | N13: 1.06 | O13: =INDEX($G13:$N13,1,MATCH(Inputs!$B$16,$G$4:$N$4,0)) -> 1.69
A14: Solution-based licensing | B14: Backup and Disaster Recovery | C14: G2 | D14: SBDHMSENS | E14: BDR - WL - Server (3 TB of Acronis Hosted Storage included) - G2 - Acronis Cyber Protect Cloud | F14: Bundles | G14: 81.5 | H14: 75.8 | I14: 69.74 | J14: 62.77 | K14: 57.75 | L14: 55.44 | M14: 52.67 | N14: 51.62 | O14: =INDEX($G14:$N14,1,MATCH(Inputs!$B$16,$G$4:$N$4,0)) -> 69.74
A15: Solution-based licensing | B15: Backup and Disaster Recovery | C15: G2 | D15: SBDIMSENS | E15: BDR - WL - VM (2 TB of Acronis Hosted Storage included) - G2 - Acronis Cyber Protect Cloud | F15: Bundles | G15: 56.5 | H15: 52.55 | I15: 48.35 | J15: 43.52 | K15: 40.04 | L15: 38.44 | M15: 36.52 | N15: 35.79 | O15: =INDEX($G15:$N15,1,MATCH(Inputs!$B$16,$G$4:$N$4,0)) -> 48.35
A16: Solution-based licensing | B16: Backup and Disaster Recovery | C16: G2 | D16: SBDJMSENS | E16: BDR - WL - Workstation (300 GB of Acronis Hosted Storage included) - G2 - Acronis Cyber Protect Cloud | F16: Bundles | G16: 11.3 | H16: 10.51 | I16: 9.67 | J16: 8.51 | K16: 7.74 | L16: 7.28 | M16: 6.84 | N16: 6.7 | O16: =INDEX($G16:$N16,1,MATCH(Inputs!$B$16,$G$4:$N$4,0)) -> 9.67
... A107: Service-based licensing | B107: Email Archiving | C107: All | D107: SH2AMSENS | E107: Email Archiving - GB - Azure Hosted Storage (per GB) - Acronis Cyber Protect Cloud | F107: Storage | G107: 0.121 | H107: 0.115 | I107: 0.107 | J107: 0.0963 | K107: 0.0886 | L107: 0.0851 | M107: 0.0817 | N107: 0.0801 | O107: =INDEX($G107:$N107,1,MATCH(Inputs!$B$16,$G$4:$N$4,0)) -> 0.107
A108: Cyber Frame | C108: All | D108: SFLAMSENS | E108: Cyber Frame Local - 1 Physical CPU Core - Acronis Cyber Protect Cloud | F108: Infrastructure | G108: 10.5 | H108: 10 | I108: 9.6 | J108: 9 | K108: 8.2 | L108: 7.5 | M108: 6.9 | N108: 6.5 | O108: =INDEX($G108:$N108,1,MATCH(Inputs!$B$16,$G$4:$N$4,0)) -> 9.6
A109: Cyber Frame | C109: All | D109: SFCAMSENS | E109: Cyber Frame Cloud - vCPU, consumed vCPU, per month3 - Acronis Cyber Protect Cloud 4 | F109: Infrastructure | G109: 9.22 | H109: 8.78 | I109: 8.43 | J109: 7.9 | K109: 7.2 | L109: 6.59 | M109: 6.06 | N109: 5.71 | O109: =INDEX($G109:$N109,1,MATCH(Inputs!$B$16,$G$4:$N$4,0)) -> 8.43
A110: Cyber Frame | C110: All | D110: SFCRMSENS | E110: Cyber Frame Cloud - RAM, consumed GB, per month3 - Acronis Cyber Protect Cloud 4 | F110: Infrastructure | G110: 2.88 | H110: 2.74 | I110: 2.63 | J110: 2.47 | K110: 2.25 | L110: 2.06 | M110: 1.89 | N110: 1.78 | O110: =INDEX($G110:$N110,1,MATCH(Inputs!$B$16,$G$4:$N$4,0)) -> 2.63
A111: Cyber Frame | C111: All | D111: SFCHMSENS | E111: Cyber Frame Cloud - Block Storage, consumed GB, per month3 - Acronis Cyber Protect Cloud 4 | F111: Infrastructure | G111: 0.1146 | H111: 0.1091 | I111: 0.1047 | J111: 0.0982 | K111: 0.0895 | L111: 0.0819 | M111: 0.0753 | N111: 0.0709 | O111: =INDEX($G111:$N111,1,MATCH(Inputs!$B$16,$G$4:$N$4,0)) -> 0.1047
A112: Cyber Frame | C112: All | D112: SFCIMSENS | E112: Cyber Frame Cloud - Public Floating IPv4, allocated IP addresses, per month3 - Acronis Cyber Protect Cloud 4 | F112: Infrastructure | G112: 3 | H112: 2.79 | I112: 2.57 | J112: 2.31 | K112: 2.13 | L112: 2.04 | M112: 1.94 | N112: 1.9 | O112: =INDEX($G112:$N112,1,MATCH(Inputs!$B$16,$G$4:$N$4,0)) -> 2.57
A113: Cyber Frame | C113: All | D113: SFCWMSENS | E113: Cyber Frame Cloud - Windows Server License, per licensed vCPU, per month3 - Acronis Cyber Protect Cloud 4 | F113: Infrastructure | G113: 11.5 | H113: 11 | I113: 10.5 | J113: 10 | K113: 9.5 | L113: 9 | M113: 8.5 | N113: 8 | O113: =INDEX($G113:$N113,1,MATCH(Inputs!$B$16,$G$4:$N$4,0)) -> 10.5
A114: Cyber Workspace | C114: G1 | D114: SWWAMSENS | E114: Cyber Workspace - Cyber Employee - Agent - Acronis Cyber Protect Cloud 4 | F114: Infrastructure | G114: 12 | H114: 11.69 | I114: 11.45 | J114: 11.2 | K114: 10.96 | L114: 10.72 | M114: 10.48 | N114: 10.24 | O114: =INDEX($G114:$N114,1,MATCH(Inputs!$B$16,$G$4:$N$4,0)) -> 11.45
A115: Cyber Workspace | C115: G1 | D115: SWWBMSENS | E115: Cyber Workspace - Cyber Employee - Usage Unit - Acronis Cyber Protect Cloud 4 | F115: Infrastructure | G115: 1 | H115: 0.97 | I115: 0.95 | J115: 0.93 | K115: 0.91 | L115: 0.89 | M115: 0.87 | N115: 0.85 | O115: =INDEX($G115:$N115,1,MATCH(Inputs!$B$16,$G$4:$N$4,0)) -> 0.95
A116: Files Sync & Share | C116: All | D116: SPIAMSENS | E116: Files Sync & Share - User (per user) - Acronis Cyber Files Cloud | F116: Backup & DR | G116: 1.7 | H116: 1.51 | I116: 1.36 | J116: 1.12 | K116: 0.99 | L116: 0.93 | M116: 0.89 | N116: 0.85 | O116: =INDEX($G116:$N116,1,MATCH(Inputs!$B$16,$G$4:$N$4,0)) -> 1.36
A117: Files Sync & Share | C117: G1 | D117: SUVAMSENS | E117: Files Sync & Share - User - Acronis Hosted Storage (per GB) - G1 - Acronis Cyber Files Cloud | F117: Storage | G117: 0.0435 | H117: 0.0387 | I117: 0.0341 | J117: 0.0286 | K117: 0.0232 | L117: 0.0218 | M117: 0.0209 | N117: 0.0203 | O117: =INDEX($G117:$N117,1,MATCH(Inputs!$B$16,$G$4:$N$4,0)) -> 0.0341
A118: Files Sync & Share | C118: G2 | D118: SUV2MSENS | E118: Files Sync & Share - User - Acronis Hosted Storage (per GB) - G2 - Acronis Cyber Files Cloud | F118: Storage | G118: 0.0546 | H118: 0.0486 | I118: 0.0428 | J118: 0.036 | K118: 0.0292 | L118: 0.0274 | M118: 0.0263 | N118: 0.0258 | O118: =INDEX($G118:$N118,1,MATCH(Inputs!$B$16,$G$4:$N$4,0)) -> 0.0428
A119: Files Sync & Share | C119: G1 | D119: SP1AMSENS | E119: Files Sync & Share - GB - Acronis Hosted Storage (per GB) - G1 - Acronis Cyber Files Cloud | F119: Storage | G119: 0.124 | H119: 0.1104 | I119: 0.0972 | J119: 0.0885 | K119: 0.0832 | L119: 0.0799 | M119: 0.0767 | N119: 0.0744 | O119: =INDEX($G119:$N119,1,MATCH(Inputs!$B$16,$G$4:$N$4,0)) -> 0.0972
... A123: Cyber Infrastructure | C123: All | D123: SCVAMSENS | E123: SPLA - Acronis Cyber Infrastructure (per GB) | F123: Infrastructure | G123: 0.015 | H123: 0.0134 | I123: 0.0118 | J123: 0.0104 | K123: 0.0094 | L123: 0.009 | M123: 0.0086 | N123: 0.0083 | O123: =INDEX($G123:$N123,1,MATCH(Inputs!$B$16,$G$4:$N$4,0)) -> 0.0118

Sheet Quote
A1: Quote builder (internal)
A2: Customer: | B2: =Inputs!B10 -> Example Trading Co. (illustrative)
A3: Currency: | B3: =Inputs!B13 -> SAR | C3: FX rate: | D3: =Inputs!B14 -> 3.75 | E3: Tier: | F3: =Inputs!B16 -> 1000
A5: Pick a SKU name from the dropdown in column B and enter the quantity in column F. Override the margin in column J only when the deal needs it.
A7: # | B7: SKU name | C7: SKU code | D7: Category | E7: DC group | F7: Quantity | G7: Unit buy (USD) | H7: Margin family | I7: Default margin | J7: Margin override | K7: Margin used | L7: Unit sell (USD) | M7: Unit sell (local) | N7: Monthly buy (USD) | O7: Monthly sell (local) | P7: Annual sell (local)
A8: 1 | B8: Ultimate Protection - WL - Server (3 TB of Acronis Hosted Storage included) - G2 - Acronis Cyber Protect Cloud | C8: =IF($B8="","",INDEX(Pricelist!$D$5:$D$123,MATCH($B8,Pricelist!$E$5:$E$123,0))) -> SUPHMSENS | D8: =IF($B8="","",INDEX(Pricelist!$B$5:$B$123,MATCH($B8,Pricelist!$E$5:$E$123,0))) -> Ultimate Protection | E8: =IF($B8="","",INDEX(Pricelist!$C$5:$C$123,MATCH($B8,Pricelist!$E$5:$E$123,0))) -> G2 | F8: 2 | G8: =IF($B8="","",INDEX(Pricelist!$O$5:$O$123,MATCH($B8,Pricelist!$E$5:$E$123,0))) -> 74.87 | H8: =IF($B8="","",INDEX(Pricelist!$F$5:$F$123,MATCH($B8,Pricelist!$E$5:$E$123,0))) -> Bundles | I8: =IF($B8="","",INDEX(Inputs!$B$24:$B$30,MATCH($H8,Inputs!$A$24:$A$30,0))) -> 0.35 | K8: =IF($B8="","",IF($J8="",$I8,$J8)) -> 0.35 | L8: =IF($B8="","",IF($K8>=1,"margin must be below 100%",$G8/(1-$K8))) -> 115.18462 | M8: =IF($B8="","",ROUND($L8*Inputs!$B$14,Inputs!$B$19)) -> 431.94 | N8: =IF($B8="","",$F8*$G8) -> 149.74 | O8: =IF($B8="","",$F8*$M8) -> 863.88 | P8: =IF($B8="","",$O8*12) -> 10366.56
A9: 2 | B9: Ultimate Protection - WL - Workstation (300 GB of Acronis Hosted Storage included) - G2 - Acronis Cyber Protect Cloud | C9: =IF($B9="","",INDEX(Pricelist!$D$5:$D$123,MATCH($B9,Pricelist!$E$5:$E$123,0))) -> SUPJMSENS | D9: =IF($B9="","",INDEX(Pricelist!$B$5:$B$123,MATCH($B9,Pricelist!$E$5:$E$123,0))) -> Ultimate Protection | E9: =IF($B9="","",INDEX(Pricelist!$C$5:$C$123,MATCH($B9,Pricelist!$E$5:$E$123,0))) -> G2 | F9: 25 | G9: =IF($B9="","",INDEX(Pricelist!$O$5:$O$123,MATCH($B9,Pricelist!$E$5:$E$123,0))) -> 13.86 | H9: =IF($B9="","",INDEX(Pricelist!$F$5:$F$123,MATCH($B9,Pricelist!$E$5:$E$123,0))) -> Bundles | I9: =IF($B9="","",INDEX(Inputs!$B$24:$B$30,MATCH($H9,Inputs!$A$24:$A$30,0))) -> 0.35 | K9: =IF($B9="","",IF($J9="",$I9,$J9)) -> 0.35 | L9: =IF($B9="","",IF($K9>=1,"margin must be below 100%",$G9/(1-$K9))) -> 21.323077 | M9: =IF($B9="","",ROUND($L9*Inputs!$B$14,Inputs!$B$19)) -> 79.96 | N9: =IF($B9="","",$F9*$G9) -> 346.5 | O9: =IF($B9="","",$F9*$M9) -> 1999 | P9: =IF($B9="","",$O9*12) -> 23988
A10: 3 | B10: Ultimate Protection - WL - Microsoft 365 seat (unlimited Acronis Hosted Cloud Storage included1) - G2 - Acronis Cyber Protect Cloud | C10: =IF($B10="","",INDEX(Pricelist!$D$5:$D$123,MATCH($B10,Pricelist!$E$5:$E$123,0))) -> SUPKMSENS | D10: =IF($B10="","",INDEX(Pricelist!$B$5:$B$123,MATCH($B10,Pricelist!$E$5:$E$123,0))) -> Ultimate Protection | E10: =IF($B10="","",INDEX(Pricelist!$C$5:$C$123,MATCH($B10,Pricelist!$E$5:$E$123,0))) -> G2 | F10: 30 | G10: =IF($B10="","",INDEX(Pricelist!$O$5:$O$123,MATCH($B10,Pricelist!$E$5:$E$123,0))) -> 8.49 | H10: =IF($B10="","",INDEX(Pricelist!$F$5:$F$123,MATCH($B10,Pricelist!$E$5:$E$123,0))) -> Bundles | I10: =IF($B10="","",INDEX(Inputs!$B$24:$B$30,MATCH($H10,Inputs!$A$24:$A$30,0))) -> 0.35 | K10: =IF($B10="","",IF($J10="",$I10,$J10)) -> 0.35 | L10: =IF($B10="","",IF($K10>=1,"margin must be below 100%",$G10/(1-$K10))) -> 13.061538 | M10: =IF($B10="","",ROUND($L10*Inputs!$B$14,Inputs!$B$19)) -> 48.98 | N10: =IF($B10="","",$F10*$G10) -> 254.7 | O10: =IF($B10="","",$F10*$M10) -> 1469.4 | P10: =IF($B10="","",$O10*12) -> 17632.8
A11: 4 | B11: Solution-based Licensing - Security Awareness Training (per user) - Acronis Cyber Protect Cloud | C11: =IF($B11="","",INDEX(Pricelist!$D$5:$D$123,MATCH($B11,Pricelist!$E$5:$E$123,0))) -> SBSTFNLOS | D11: =IF($B11="","",INDEX(Pricelist!$B$5:$B$123,MATCH($B11,Pricelist!$E$5:$E$123,0))) -> Security Awareness Training | E11: =IF($B11="","",INDEX(Pricelist!$C$5:$C$123,MATCH($B11,Pricelist!$E$5:$E$123,0))) -> All | F11: 30 | G11: =IF($B11="","",INDEX(Pricelist!$O$5:$O$123,MATCH($B11,Pricelist!$E$5:$E$123,0))) -> 1.24 | H11: =IF($B11="","",INDEX(Pricelist!$F$5:$F$123,MATCH($B11,Pricelist!$E$5:$E$123,0))) -> Bundles | I11: =IF($B11="","",INDEX(Inputs!$B$24:$B$30,MATCH($H11,Inputs!$A$24:$A$30,0))) -> 0.35 | K11: =IF($B11="","",IF($J11="",$I11,$J11)) -> 0.35 | L11: =IF($B11="","",IF($K11>=1,"margin must be below 100%",$G11/(1-$K11))) -> 1.9076923 | M11: =IF($B11="","",ROUND($L11*Inputs!$B$14,Inputs!$B$19)) -> 7.15 | N11: =IF($B11="","",$F11*$G11) -> 37.2 | O11: =IF($B11="","",$F11*$M11) -> 214.5 | P11: =IF($B11="","",$O11*12) -> 2574
A12: 5 | C12: =IF($B12="","",INDEX(Pricelist!$D$5:$D$123,MATCH($B12,Pricelist!$E$5:$E$123,0))) | D12: =IF($B12="","",INDEX(Pricelist!$B$5:$B$123,MATCH($B12,Pricelist!$E$5:$E$123,0))) | E12: =IF($B12="","",INDEX(Pricelist!$C$5:$C$123,MATCH($B12,Pricelist!$E$5:$E$123,0))) | G12: =IF($B12="","",INDEX(Pricelist!$O$5:$O$123,MATCH($B12,Pricelist!$E$5:$E$123,0))) | H12: =IF($B12="","",INDEX(Pricelist!$F$5:$F$123,MATCH($B12,Pricelist!$E$5:$E$123,0))) | I12: =IF($B12="","",INDEX(Inputs!$B$24:$B$30,MATCH($H12,Inputs!$A$24:$A$30,0))) | K12: =IF($B12="","",IF($J12="",$I12,$J12)) | L12: =IF($B12="","",IF($K12>=1,"margin must be below 100%",$G12/(1-$K12))) | M12: =IF($B12="","",ROUND($L12*Inputs!$B$14,Inputs!$B$19)) | N12: =IF($B12="","",$F12*$G12) | O12: =IF($B12="","",$F12*$M12) | P12: =IF($B12="","",$O12*12)
A13: 6 | C13: =IF($B13="","",INDEX(Pricelist!$D$5:$D$123,MATCH($B13,Pricelist!$E$5:$E$123,0))) | D13: =IF($B13="","",INDEX(Pricelist!$B$5:$B$123,MATCH($B13,Pricelist!$E$5:$E$123,0))) | E13: =IF($B13="","",INDEX(Pricelist!$C$5:$C$123,MATCH($B13,Pricelist!$E$5:$E$123,0))) | G13: =IF($B13="","",INDEX(Pricelist!$O$5:$O$123,MATCH($B13,Pricelist!$E$5:$E$123,0))) | H13: =IF($B13="","",INDEX(Pricelist!$F$5:$F$123,MATCH($B13,Pricelist!$E$5:$E$123,0))) | I13: =IF($B13="","",INDEX(Inputs!$B$24:$B$30,MATCH($H13,Inputs!$A$24:$A$30,0))) | K13: =IF($B13="","",IF($J13="",$I13,$J13)) | L13: =IF($B13="","",IF($K13>=1,"margin must be below 100%",$G13/(1-$K13))) | M13: =IF($B13="","",ROUND($L13*Inputs!$B$14,Inputs!$B$19)) | N13: =IF($B13="","",$F13*$G13) | O13: =IF($B13="","",$F13*$M13) | P13: =IF($B13="","",$O13*12)
A14: 7 | C14: =IF($B14="","",INDEX(Pricelist!$D$5:$D$123,MATCH($B14,Pricelist!$E$5:$E$123,0))) | D14: =IF($B14="","",INDEX(Pricelist!$B$5:$B$123,MATCH($B14,Pricelist!$E$5:$E$123,0))) | E14: =IF($B14="","",INDEX(Pricelist!$C$5:$C$123,MATCH($B14,Pricelist!$E$5:$E$123,0))) | G14: =IF($B14="","",INDEX(Pricelist!$O$5:$O$123,MATCH($B14,Pricelist!$E$5:$E$123,0))) | H14: =IF($B14="","",INDEX(Pricelist!$F$5:$F$123,MATCH($B14,Pricelist!$E$5:$E$123,0))) | I14: =IF($B14="","",INDEX(Inputs!$B$24:$B$30,MATCH($H14,Inputs!$A$24:$A$30,0))) | K14: =IF($B14="","",IF($J14="",$I14,$J14)) | L14: =IF($B14="","",IF($K14>=1,"margin must be below 100%",$G14/(1-$K14))) | M14: =IF($B14="","",ROUND($L14*Inputs!$B$14,Inputs!$B$19)) | N14: =IF($B14="","",$F14*$G14) | O14: =IF($B14="","",$F14*$M14) | P14: =IF($B14="","",$O14*12)
A15: 8 | C15: =IF($B15="","",INDEX(Pricelist!$D$5:$D$123,MATCH($B15,Pricelist!$E$5:$E$123,0))) | D15: =IF($B15="","",INDEX(Pricelist!$B$5:$B$123,MATCH($B15,Pricelist!$E$5:$E$123,0))) | E15: =IF($B15="","",INDEX(Pricelist!$C$5:$C$123,MATCH($B15,Pricelist!$E$5:$E$123,0))) | G15: =IF($B15="","",INDEX(Pricelist!$O$5:$O$123,MATCH($B15,Pricelist!$E$5:$E$123,0))) | H15: =IF($B15="","",INDEX(Pricelist!$F$5:$F$123,MATCH($B15,Pricelist!$E$5:$E$123,0))) | I15: =IF($B15="","",INDEX(Inputs!$B$24:$B$30,MATCH($H15,Inputs!$A$24:$A$30,0))) | K15: =IF($B15="","",IF($J15="",$I15,$J15)) | L15: =IF($B15="","",IF($K15>=1,"margin must be below 100%",$G15/(1-$K15))) | M15: =IF($B15="","",ROUND($L15*Inputs!$B$14,Inputs!$B$19)) | N15: =IF($B15="","",$F15*$G15) | O15: =IF($B15="","",$F15*$M15) | P15: =IF($B15="","",$O15*12)
A16: 9 | C16: =IF($B16="","",INDEX(Pricelist!$D$5:$D$123,MATCH($B16,Pricelist!$E$5:$E$123,0))) | D16: =IF($B16="","",INDEX(Pricelist!$B$5:$B$123,MATCH($B16,Pricelist!$E$5:$E$123,0))) | E16: =IF($B16="","",INDEX(Pricelist!$C$5:$C$123,MATCH($B16,Pricelist!$E$5:$E$123,0))) | G16: =IF($B16="","",INDEX(Pricelist!$O$5:$O$123,MATCH($B16,Pricelist!$E$5:$E$123,0))) | H16: =IF($B16="","",INDEX(Pricelist!$F$5:$F$123,MATCH($B16,Pricelist!$E$5:$E$123,0))) | I16: =IF($B16="","",INDEX(Inputs!$B$24:$B$30,MATCH($H16,Inputs!$A$24:$A$30,0))) | K16: =IF($B16="","",IF($J16="",$I16,$J16)) | L16: =IF($B16="","",IF($K16>=1,"margin must be below 100%",$G16/(1-$K16))) | M16: =IF($B16="","",ROUND($L16*Inputs!$B$14,Inputs!$B$19)) | N16: =IF($B16="","",$F16*$G16) | O16: =IF($B16="","",$F16*$M16) | P16: =IF($B16="","",$O16*12)
A17: 10 | C17: =IF($B17="","",INDEX(Pricelist!$D$5:$D$123,MATCH($B17,Pricelist!$E$5:$E$123,0))) | D17: =IF($B17="","",INDEX(Pricelist!$B$5:$B$123,MATCH($B17,Pricelist!$E$5:$E$123,0))) | E17: =IF($B17="","",INDEX(Pricelist!$C$5:$C$123,MATCH($B17,Pricelist!$E$5:$E$123,0))) | G17: =IF($B17="","",INDEX(Pricelist!$O$5:$O$123,MATCH($B17,Pricelist!$E$5:$E$123,0))) | H17: =IF($B17="","",INDEX(Pricelist!$F$5:$F$123,MATCH($B17,Pricelist!$E$5:$E$123,0))) | I17: =IF($B17="","",INDEX(Inputs!$B$24:$B$30,MATCH($H17,Inputs!$A$24:$A$30,0))) | K17: =IF($B17="","",IF($J17="",$I17,$J17)) | L17: =IF($B17="","",IF($K17>=1,"margin must be below 100%",$G17/(1-$K17))) | M17: =IF($B17="","",ROUND($L17*Inputs!$B$14,Inputs!$B$19)) | N17: =IF($B17="","",$F17*$G17) | O17: =IF($B17="","",$F17*$M17) | P17: =IF($B17="","",$O17*12)
A18: 11 | C18: =IF($B18="","",INDEX(Pricelist!$D$5:$D$123,MATCH($B18,Pricelist!$E$5:$E$123,0))) | D18: =IF($B18="","",INDEX(Pricelist!$B$5:$B$123,MATCH($B18,Pricelist!$E$5:$E$123,0))) | E18: =IF($B18="","",INDEX(Pricelist!$C$5:$C$123,MATCH($B18,Pricelist!$E$5:$E$123,0))) | G18: =IF($B18="","",INDEX(Pricelist!$O$5:$O$123,MATCH($B18,Pricelist!$E$5:$E$123,0))) | H18: =IF($B18="","",INDEX(Pricelist!$F$5:$F$123,MATCH($B18,Pricelist!$E$5:$E$123,0))) | I18: =IF($B18="","",INDEX(Inputs!$B$24:$B$30,MATCH($H18,Inputs!$A$24:$A$30,0))) | K18: =IF($B18="","",IF($J18="",$I18,$J18)) | L18: =IF($B18="","",IF($K18>=1,"margin must be below 100%",$G18/(1-$K18))) | M18: =IF($B18="","",ROUND($L18*Inputs!$B$14,Inputs!$B$19)) | N18: =IF($B18="","",$F18*$G18) | O18: =IF($B18="","",$F18*$M18) | P18: =IF($B18="","",$O18*12)
A19: 12 | C19: =IF($B19="","",INDEX(Pricelist!$D$5:$D$123,MATCH($B19,Pricelist!$E$5:$E$123,0))) | D19: =IF($B19="","",INDEX(Pricelist!$B$5:$B$123,MATCH($B19,Pricelist!$E$5:$E$123,0))) | E19: =IF($B19="","",INDEX(Pricelist!$C$5:$C$123,MATCH($B19,Pricelist!$E$5:$E$123,0))) | G19: =IF($B19="","",INDEX(Pricelist!$O$5:$O$123,MATCH($B19,Pricelist!$E$5:$E$123,0))) | H19: =IF($B19="","",INDEX(Pricelist!$F$5:$F$123,MATCH($B19,Pricelist!$E$5:$E$123,0))) | I19: =IF($B19="","",INDEX(Inputs!$B$24:$B$30,MATCH($H19,Inputs!$A$24:$A$30,0))) | K19: =IF($B19="","",IF($J19="",$I19,$J19)) | L19: =IF($B19="","",IF($K19>=1,"margin must be below 100%",$G19/(1-$K19))) | M19: =IF($B19="","",ROUND($L19*Inputs!$B$14,Inputs!$B$19)) | N19: =IF($B19="","",$F19*$G19) | O19: =IF($B19="","",$F19*$M19) | P19: =IF($B19="","",$O19*12)
A20: 13 | C20: =IF($B20="","",INDEX(Pricelist!$D$5:$D$123,MATCH($B20,Pricelist!$E$5:$E$123,0))) | D20: =IF($B20="","",INDEX(Pricelist!$B$5:$B$123,MATCH($B20,Pricelist!$E$5:$E$123,0))) | E20: =IF($B20="","",INDEX(Pricelist!$C$5:$C$123,MATCH($B20,Pricelist!$E$5:$E$123,0))) | G20: =IF($B20="","",INDEX(Pricelist!$O$5:$O$123,MATCH($B20,Pricelist!$E$5:$E$123,0))) | H20: =IF($B20="","",INDEX(Pricelist!$F$5:$F$123,MATCH($B20,Pricelist!$E$5:$E$123,0))) | I20: =IF($B20="","",INDEX(Inputs!$B$24:$B$30,MATCH($H20,Inputs!$A$24:$A$30,0))) | K20: =IF($B20="","",IF($J20="",$I20,$J20)) | L20: =IF($B20="","",IF($K20>=1,"margin must be below 100%",$G20/(1-$K20))) | M20: =IF($B20="","",ROUND($L20*Inputs!$B$14,Inputs!$B$19)) | N20: =IF($B20="","",$F20*$G20) | O20: =IF($B20="","",$F20*$M20) | P20: =IF($B20="","",$O20*12)
A21: 14 | C21: =IF($B21="","",INDEX(Pricelist!$D$5:$D$123,MATCH($B21,Pricelist!$E$5:$E$123,0))) | D21: =IF($B21="","",INDEX(Pricelist!$B$5:$B$123,MATCH($B21,Pricelist!$E$5:$E$123,0))) | E21: =IF($B21="","",INDEX(Pricelist!$C$5:$C$123,MATCH($B21,Pricelist!$E$5:$E$123,0))) | G21: =IF($B21="","",INDEX(Pricelist!$O$5:$O$123,MATCH($B21,Pricelist!$E$5:$E$123,0))) | H21: =IF($B21="","",INDEX(Pricelist!$F$5:$F$123,MATCH($B21,Pricelist!$E$5:$E$123,0))) | I21: =IF($B21="","",INDEX(Inputs!$B$24:$B$30,MATCH($H21,Inputs!$A$24:$A$30,0))) | K21: =IF($B21="","",IF($J21="",$I21,$J21)) | L21: =IF($B21="","",IF($K21>=1,"margin must be below 100%",$G21/(1-$K21))) | M21: =IF($B21="","",ROUND($L21*Inputs!$B$14,Inputs!$B$19)) | N21: =IF($B21="","",$F21*$G21) | O21: =IF($B21="","",$F21*$M21) | P21: =IF($B21="","",$O21*12)
A22: 15 | C22: =IF($B22="","",INDEX(Pricelist!$D$5:$D$123,MATCH($B22,Pricelist!$E$5:$E$123,0))) | D22: =IF($B22="","",INDEX(Pricelist!$B$5:$B$123,MATCH($B22,Pricelist!$E$5:$E$123,0))) | E22: =IF($B22="","",INDEX(Pricelist!$C$5:$C$123,MATCH($B22,Pricelist!$E$5:$E$123,0))) | G22: =IF($B22="","",INDEX(Pricelist!$O$5:$O$123,MATCH($B22,Pricelist!$E$5:$E$123,0))) | H22: =IF($B22="","",INDEX(Pricelist!$F$5:$F$123,MATCH($B22,Pricelist!$E$5:$E$123,0))) | I22: =IF($B22="","",INDEX(Inputs!$B$24:$B$30,MATCH($H22,Inputs!$A$24:$A$30,0))) | K22: =IF($B22="","",IF($J22="",$I22,$J22)) | L22: =IF($B22="","",IF($K22>=1,"margin must be below 100%",$G22/(1-$K22))) | M22: =IF($B22="","",ROUND($L22*Inputs!$B$14,Inputs!$B$19)) | N22: =IF($B22="","",$F22*$G22) | O22: =IF($B22="","",$F22*$M22) | P22: =IF($B22="","",$O22*12)
A23: 16 | C23: =IF($B23="","",INDEX(Pricelist!$D$5:$D$123,MATCH($B23,Pricelist!$E$5:$E$123,0))) | D23: =IF($B23="","",INDEX(Pricelist!$B$5:$B$123,MATCH($B23,Pricelist!$E$5:$E$123,0))) | E23: =IF($B23="","",INDEX(Pricelist!$C$5:$C$123,MATCH($B23,Pricelist!$E$5:$E$123,0))) | G23: =IF($B23="","",INDEX(Pricelist!$O$5:$O$123,MATCH($B23,Pricelist!$E$5:$E$123,0))) | H23: =IF($B23="","",INDEX(Pricelist!$F$5:$F$123,MATCH($B23,Pricelist!$E$5:$E$123,0))) | I23: =IF($B23="","",INDEX(Inputs!$B$24:$B$30,MATCH($H23,Inputs!$A$24:$A$30,0))) | K23: =IF($B23="","",IF($J23="",$I23,$J23)) | L23: =IF($B23="","",IF($K23>=1,"margin must be below 100%",$G23/(1-$K23))) | M23: =IF($B23="","",ROUND($L23*Inputs!$B$14,Inputs!$B$19)) | N23: =IF($B23="","",$F23*$G23) | O23: =IF($B23="","",$F23*$M23) | P23: =IF($B23="","",$O23*12)
... A37: 30 | C37: =IF($B37="","",INDEX(Pricelist!$D$5:$D$123,MATCH($B37,Pricelist!$E$5:$E$123,0))) | D37: =IF($B37="","",INDEX(Pricelist!$B$5:$B$123,MATCH($B37,Pricelist!$E$5:$E$123,0))) | E37: =IF($B37="","",INDEX(Pricelist!$C$5:$C$123,MATCH($B37,Pricelist!$E$5:$E$123,0))) | G37: =IF($B37="","",INDEX(Pricelist!$O$5:$O$123,MATCH($B37,Pricelist!$E$5:$E$123,0))) | H37: =IF($B37="","",INDEX(Pricelist!$F$5:$F$123,MATCH($B37,Pricelist!$E$5:$E$123,0))) | I37: =IF($B37="","",INDEX(Inputs!$B$24:$B$30,MATCH($H37,Inputs!$A$24:$A$30,0))) | K37: =IF($B37="","",IF($J37="",$I37,$J37)) | L37: =IF($B37="","",IF($K37>=1,"margin must be below 100%",$G37/(1-$K37))) | M37: =IF($B37="","",ROUND($L37*Inputs!$B$14,Inputs!$B$19)) | N37: =IF($B37="","",$F37*$G37) | O37: =IF($B37="","",$F37*$M37) | P37: =IF($B37="","",$O37*12)
A39: Totals
A40: Platform subtotal, monthly buy (USD) | B40: =SUM(N8:N37) -> 788.14
A41: Platform subtotal, monthly buy (local) | B41: =B40*Inputs!B14 -> 2955.525
A42: Platform subtotal, monthly sell (local) | B42: =SUM(O8:O37) -> 4546.78
A43: Protected workloads and seats (excludes storage lines) | B43: =SUMIFS(F8:F37,H8:H37,"<>Storage",H8:H37,"<>Infrastructure",H8:H37,"<>Other") -> 87
A44: Managed service fee, monthly (local) | B44: =B43*Inputs!B33+Inputs!B34 -> 1305
A45: Monthly total excluding VAT (local) | B45: =B42+B44 -> 5851.78
A46: VAT (local) | B46: =B45*Inputs!B15 -> 877.767
A47: Monthly total including VAT (local) | B47: =B45+B46 -> 6729.547
A48: Annual total excluding VAT (local) | B48: =B45*12 -> 70221.36
A49: Contract value excluding VAT (local) | B49: =B45*Inputs!B17 -> 70221.36
A50: One-time services excluding VAT (local) | B50: =Inputs!B35+Inputs!B36+Inputs!B37 -> 7500
A51: Monthly gross profit on platform (local) | B51: =B42-B41 -> 1591.255
A52: Blended platform margin | B52: =IF(B42=0,0,B51/B42) -> 0.34997405
A53: Monthly gross profit including managed service (local) | B53: =B51+B44 -> 2896.255
A55: Gross profit here is sell minus Acronis buy; it excludes Next Step delivery cost and the difference between the commitment tier and actual portfolio consumption.

Sheet Tier analysis
A1: This quote's Acronis buy cost at every commitment tier (USD per month)
A2: Shows what the same quantities cost Next Step at each tier. The tier applies to the whole Next Step portfolio; use this to judge whether a deal justifies moving up a tier.
A4: # | B4: SKU name | C4: Quantity | D4: Tier 250 | E4: Tier 500 | F4: Tier 1,000 | G4: Tier 2,000 | H4: Tier 4,000 | I4: Tier 7,000 | J4: Tier 10,000 | K4: Tier 15,000
C5: Commitment → | D5: 250 | E5: 500 | F5: 1000 | G5: 2000 | H5: 4000 | I5: 7000 | J5: 10000 | K5: 15000
A6: 1 | B6: =Quote!B8 -> Ultimate Protection - WL - Server (3 TB of Acronis Hosted Storage included) - G2 - Acronis Cyber Protect Cloud | C6: =IF(Quote!B8="","",Quote!F8) -> 2 | D6: =IF(Quote!$B8="",0,Quote!$F8*INDEX(Pricelist!$G$5:$G$123,MATCH(Quote!$B8,Pricelist!$E$5:$E$123,0))) -> 175 | E6: =IF(Quote!$B8="",0,Quote!$F8*INDEX(Pricelist!$H$5:$H$123,MATCH(Quote!$B8,Pricelist!$E$5:$E$123,0))) -> 162.76 | F6: =IF(Quote!$B8="",0,Quote!$F8*INDEX(Pricelist!$I$5:$I$123,MATCH(Quote!$B8,Pricelist!$E$5:$E$123,0))) -> 149.74 | G6: =IF(Quote!$B8="",0,Quote!$F8*INDEX(Pricelist!$J$5:$J$123,MATCH(Quote!$B8,Pricelist!$E$5:$E$123,0))) -> 134.76 | H6: =IF(Quote!$B8="",0,Quote!$F8*INDEX(Pricelist!$K$5:$K$123,MATCH(Quote!$B8,Pricelist!$E$5:$E$123,0))) -> 128.02 | I6: =IF(Quote!$B8="",0,Quote!$F8*INDEX(Pricelist!$L$5:$L$123,MATCH(Quote!$B8,Pricelist!$E$5:$E$123,0))) -> 124.18 | J6: =IF(Quote!$B8="",0,Quote!$F8*INDEX(Pricelist!$M$5:$M$123,MATCH(Quote!$B8,Pricelist!$E$5:$E$123,0))) -> 120.46 | K6: =IF(Quote!$B8="",0,Quote!$F8*INDEX(Pricelist!$N$5:$N$123,MATCH(Quote!$B8,Pricelist!$E$5:$E$123,0))) -> 118.06
A7: 2 | B7: =Quote!B9 -> Ultimate Protection - WL - Workstation (300 GB of Acronis Hosted Storage included) - G2 - Acronis Cyber Protect Cloud | C7: =IF(Quote!B9="","",Quote!F9) -> 25 | D7: =IF(Quote!$B9="",0,Quote!$F9*INDEX(Pricelist!$G$5:$G$123,MATCH(Quote!$B9,Pricelist!$E$5:$E$123,0))) -> 405 | E7: =IF(Quote!$B9="",0,Quote!$F9*INDEX(Pricelist!$H$5:$H$123,MATCH(Quote!$B9,Pricelist!$E$5:$E$123,0))) -> 376.75 | F7: =IF(Quote!$B9="",0,Quote!$F9*INDEX(Pricelist!$I$5:$I$123,MATCH(Quote!$B9,Pricelist!$E$5:$E$123,0))) -> 346.5 | G7: =IF(Quote!$B9="",0,Quote!$F9*INDEX(Pricelist!$J$5:$J$123,MATCH(Quote!$B9,Pricelist!$E$5:$E$123,0))) -> 305 | H7: =IF(Quote!$B9="",0,Quote!$F9*INDEX(Pricelist!$K$5:$K$123,MATCH(Quote!$B9,Pricelist!$E$5:$E$123,0))) -> 277.5 | I7: =IF(Quote!$B9="",0,Quote!$F9*INDEX(Pricelist!$L$5:$L$123,MATCH(Quote!$B9,Pricelist!$E$5:$E$123,0))) -> 260.75 | J7: =IF(Quote!$B9="",0,Quote!$F9*INDEX(Pricelist!$M$5:$M$123,MATCH(Quote!$B9,Pricelist!$E$5:$E$123,0))) -> 245 | K7: =IF(Quote!$B9="",0,Quote!$F9*INDEX(Pricelist!$N$5:$N$123,MATCH(Quote!$B9,Pricelist!$E$5:$E$123,0))) -> 240
A8: 3 | B8: =Quote!B10 -> Ultimate Protection - WL - Microsoft 365 seat (unlimited Acronis Hosted Cloud Storage included1) - G2 - Acronis Cyber Protect Cloud | C8: =IF(Quote!B10="","",Quote!F10) -> 30 | D8: =IF(Quote!$B10="",0,Quote!$F10*INDEX(Pricelist!$G$5:$G$123,MATCH(Quote!$B10,Pricelist!$E$5:$E$123,0))) -> 285 | E8: =IF(Quote!$B10="",0,Quote!$F10*INDEX(Pricelist!$H$5:$H$123,MATCH(Quote!$B10,Pricelist!$E$5:$E$123,0))) -> 270.9 | F8: =IF(Quote!$B10="",0,Quote!$F10*INDEX(Pricelist!$I$5:$I$123,MATCH(Quote!$B10,Pricelist!$E$5:$E$123,0))) -> 254.7 | G8: =IF(Quote!$B10="",0,Quote!$F10*INDEX(Pricelist!$J$5:$J$123,MATCH(Quote!$B10,Pricelist!$E$5:$E$123,0))) -> 234.3 | H8: =IF(Quote!$B10="",0,Quote!$F10*INDEX(Pricelist!$K$5:$K$123,MATCH(Quote!$B10,Pricelist!$E$5:$E$123,0))) -> 215.7 | I8: =IF(Quote!$B10="",0,Quote!$F10*INDEX(Pricelist!$L$5:$L$123,MATCH(Quote!$B10,Pricelist!$E$5:$E$123,0))) -> 209.1 | J8: =IF(Quote!$B10="",0,Quote!$F10*INDEX(Pricelist!$M$5:$M$123,MATCH(Quote!$B10,Pricelist!$E$5:$E$123,0))) -> 202.8 | K8: =IF(Quote!$B10="",0,Quote!$F10*INDEX(Pricelist!$N$5:$N$123,MATCH(Quote!$B10,Pricelist!$E$5:$E$123,0))) -> 198.6
A9: 4 | B9: =Quote!B11 -> Solution-based Licensing - Security Awareness Training (per user) - Acronis Cyber Protect Cloud | C9: =IF(Quote!B11="","",Quote!F11) -> 30 | D9: =IF(Quote!$B11="",0,Quote!$F11*INDEX(Pricelist!$G$5:$G$123,MATCH(Quote!$B11,Pricelist!$E$5:$E$123,0))) -> 42 | E9: =IF(Quote!$B11="",0,Quote!$F11*INDEX(Pricelist!$H$5:$H$123,MATCH(Quote!$B11,Pricelist!$E$5:$E$123,0))) -> 39.9 | F9: =IF(Quote!$B11="",0,Quote!$F11*INDEX(Pricelist!$I$5:$I$123,MATCH(Quote!$B11,Pricelist!$E$5:$E$123,0))) -> 37.2 | G9: =IF(Quote!$B11="",0,Quote!$F11*INDEX(Pricelist!$J$5:$J$123,MATCH(Quote!$B11,Pricelist!$E$5:$E$123,0))) -> 33.6 | H9: =IF(Quote!$B11="",0,Quote!$F11*INDEX(Pricelist!$K$5:$K$123,MATCH(Quote!$B11,Pricelist!$E$5:$E$123,0))) -> 30.9 | I9: =IF(Quote!$B11="",0,Quote!$F11*INDEX(Pricelist!$L$5:$L$123,MATCH(Quote!$B11,Pricelist!$E$5:$E$123,0))) -> 29.7 | J9: =IF(Quote!$B11="",0,Quote!$F11*INDEX(Pricelist!$M$5:$M$123,MATCH(Quote!$B11,Pricelist!$E$5:$E$123,0))) -> 28.5 | K9: =IF(Quote!$B11="",0,Quote!$F11*INDEX(Pricelist!$N$5:$N$123,MATCH(Quote!$B11,Pricelist!$E$5:$E$123,0))) -> 27.9
A10: 5 | B10: =Quote!B12 -> 0 | C10: =IF(Quote!B12="","",Quote!F12) | D10: =IF(Quote!$B12="",0,Quote!$F12*INDEX(Pricelist!$G$5:$G$123,MATCH(Quote!$B12,Pricelist!$E$5:$E$123,0))) -> 0 | E10: =IF(Quote!$B12="",0,Quote!$F12*INDEX(Pricelist!$H$5:$H$123,MATCH(Quote!$B12,Pricelist!$E$5:$E$123,0))) -> 0 | F10: =IF(Quote!$B12="",0,Quote!$F12*INDEX(Pricelist!$I$5:$I$123,MATCH(Quote!$B12,Pricelist!$E$5:$E$123,0))) -> 0 | G10: =IF(Quote!$B12="",0,Quote!$F12*INDEX(Pricelist!$J$5:$J$123,MATCH(Quote!$B12,Pricelist!$E$5:$E$123,0))) -> 0 | H10: =IF(Quote!$B12="",0,Quote!$F12*INDEX(Pricelist!$K$5:$K$123,MATCH(Quote!$B12,Pricelist!$E$5:$E$123,0))) -> 0 | I10: =IF(Quote!$B12="",0,Quote!$F12*INDEX(Pricelist!$L$5:$L$123,MATCH(Quote!$B12,Pricelist!$E$5:$E$123,0))) -> 0 | J10: =IF(Quote!$B12="",0,Quote!$F12*INDEX(Pricelist!$M$5:$M$123,MATCH(Quote!$B12,Pricelist!$E$5:$E$123,0))) -> 0 | K10: =IF(Quote!$B12="",0,Quote!$F12*INDEX(Pricelist!$N$5:$N$123,MATCH(Quote!$B12,Pricelist!$E$5:$E$123,0))) -> 0
A11: 6 | B11: =Quote!B13 -> 0 | C11: =IF(Quote!B13="","",Quote!F13) | D11: =IF(Quote!$B13="",0,Quote!$F13*INDEX(Pricelist!$G$5:$G$123,MATCH(Quote!$B13,Pricelist!$E$5:$E$123,0))) -> 0 | E11: =IF(Quote!$B13="",0,Quote!$F13*INDEX(Pricelist!$H$5:$H$123,MATCH(Quote!$B13,Pricelist!$E$5:$E$123,0))) -> 0 | F11: =IF(Quote!$B13="",0,Quote!$F13*INDEX(Pricelist!$I$5:$I$123,MATCH(Quote!$B13,Pricelist!$E$5:$E$123,0))) -> 0 | G11: =IF(Quote!$B13="",0,Quote!$F13*INDEX(Pricelist!$J$5:$J$123,MATCH(Quote!$B13,Pricelist!$E$5:$E$123,0))) -> 0 | H11: =IF(Quote!$B13="",0,Quote!$F13*INDEX(Pricelist!$K$5:$K$123,MATCH(Quote!$B13,Pricelist!$E$5:$E$123,0))) -> 0 | I11: =IF(Quote!$B13="",0,Quote!$F13*INDEX(Pricelist!$L$5:$L$123,MATCH(Quote!$B13,Pricelist!$E$5:$E$123,0))) -> 0 | J11: =IF(Quote!$B13="",0,Quote!$F13*INDEX(Pricelist!$M$5:$M$123,MATCH(Quote!$B13,Pricelist!$E$5:$E$123,0))) -> 0 | K11: =IF(Quote!$B13="",0,Quote!$F13*INDEX(Pricelist!$N$5:$N$123,MATCH(Quote!$B13,Pricelist!$E$5:$E$123,0))) -> 0
A12: 7 | B12: =Quote!B14 -> 0 | C12: =IF(Quote!B14="","",Quote!F14) | D12: =IF(Quote!$B14="",0,Quote!$F14*INDEX(Pricelist!$G$5:$G$123,MATCH(Quote!$B14,Pricelist!$E$5:$E$123,0))) -> 0 | E12: =IF(Quote!$B14="",0,Quote!$F14*INDEX(Pricelist!$H$5:$H$123,MATCH(Quote!$B14,Pricelist!$E$5:$E$123,0))) -> 0 | F12: =IF(Quote!$B14="",0,Quote!$F14*INDEX(Pricelist!$I$5:$I$123,MATCH(Quote!$B14,Pricelist!$E$5:$E$123,0))) -> 0 | G12: =IF(Quote!$B14="",0,Quote!$F14*INDEX(Pricelist!$J$5:$J$123,MATCH(Quote!$B14,Pricelist!$E$5:$E$123,0))) -> 0 | H12: =IF(Quote!$B14="",0,Quote!$F14*INDEX(Pricelist!$K$5:$K$123,MATCH(Quote!$B14,Pricelist!$E$5:$E$123,0))) -> 0 | I12: =IF(Quote!$B14="",0,Quote!$F14*INDEX(Pricelist!$L$5:$L$123,MATCH(Quote!$B14,Pricelist!$E$5:$E$123,0))) -> 0 | J12: =IF(Quote!$B14="",0,Quote!$F14*INDEX(Pricelist!$M$5:$M$123,MATCH(Quote!$B14,Pricelist!$E$5:$E$123,0))) -> 0 | K12: =IF(Quote!$B14="",0,Quote!$F14*INDEX(Pricelist!$N$5:$N$123,MATCH(Quote!$B14,Pricelist!$E$5:$E$123,0))) -> 0
A13: 8 | B13: =Quote!B15 -> 0 | C13: =IF(Quote!B15="","",Quote!F15) | D13: =IF(Quote!$B15="",0,Quote!$F15*INDEX(Pricelist!$G$5:$G$123,MATCH(Quote!$B15,Pricelist!$E$5:$E$123,0))) -> 0 | E13: =IF(Quote!$B15="",0,Quote!$F15*INDEX(Pricelist!$H$5:$H$123,MATCH(Quote!$B15,Pricelist!$E$5:$E$123,0))) -> 0 | F13: =IF(Quote!$B15="",0,Quote!$F15*INDEX(Pricelist!$I$5:$I$123,MATCH(Quote!$B15,Pricelist!$E$5:$E$123,0))) -> 0 | G13: =IF(Quote!$B15="",0,Quote!$F15*INDEX(Pricelist!$J$5:$J$123,MATCH(Quote!$B15,Pricelist!$E$5:$E$123,0))) -> 0 | H13: =IF(Quote!$B15="",0,Quote!$F15*INDEX(Pricelist!$K$5:$K$123,MATCH(Quote!$B15,Pricelist!$E$5:$E$123,0))) -> 0 | I13: =IF(Quote!$B15="",0,Quote!$F15*INDEX(Pricelist!$L$5:$L$123,MATCH(Quote!$B15,Pricelist!$E$5:$E$123,0))) -> 0 | J13: =IF(Quote!$B15="",0,Quote!$F15*INDEX(Pricelist!$M$5:$M$123,MATCH(Quote!$B15,Pricelist!$E$5:$E$123,0))) -> 0 | K13: =IF(Quote!$B15="",0,Quote!$F15*INDEX(Pricelist!$N$5:$N$123,MATCH(Quote!$B15,Pricelist!$E$5:$E$123,0))) -> 0
A14: 9 | B14: =Quote!B16 -> 0 | C14: =IF(Quote!B16="","",Quote!F16) | D14: =IF(Quote!$B16="",0,Quote!$F16*INDEX(Pricelist!$G$5:$G$123,MATCH(Quote!$B16,Pricelist!$E$5:$E$123,0))) -> 0 | E14: =IF(Quote!$B16="",0,Quote!$F16*INDEX(Pricelist!$H$5:$H$123,MATCH(Quote!$B16,Pricelist!$E$5:$E$123,0))) -> 0 | F14: =IF(Quote!$B16="",0,Quote!$F16*INDEX(Pricelist!$I$5:$I$123,MATCH(Quote!$B16,Pricelist!$E$5:$E$123,0))) -> 0 | G14: =IF(Quote!$B16="",0,Quote!$F16*INDEX(Pricelist!$J$5:$J$123,MATCH(Quote!$B16,Pricelist!$E$5:$E$123,0))) -> 0 | H14: =IF(Quote!$B16="",0,Quote!$F16*INDEX(Pricelist!$K$5:$K$123,MATCH(Quote!$B16,Pricelist!$E$5:$E$123,0))) -> 0 | I14: =IF(Quote!$B16="",0,Quote!$F16*INDEX(Pricelist!$L$5:$L$123,MATCH(Quote!$B16,Pricelist!$E$5:$E$123,0))) -> 0 | J14: =IF(Quote!$B16="",0,Quote!$F16*INDEX(Pricelist!$M$5:$M$123,MATCH(Quote!$B16,Pricelist!$E$5:$E$123,0))) -> 0 | K14: =IF(Quote!$B16="",0,Quote!$F16*INDEX(Pricelist!$N$5:$N$123,MATCH(Quote!$B16,Pricelist!$E$5:$E$123,0))) -> 0
A15: 10 | B15: =Quote!B17 -> 0 | C15: =IF(Quote!B17="","",Quote!F17) | D15: =IF(Quote!$B17="",0,Quote!$F17*INDEX(Pricelist!$G$5:$G$123,MATCH(Quote!$B17,Pricelist!$E$5:$E$123,0))) -> 0 | E15: =IF(Quote!$B17="",0,Quote!$F17*INDEX(Pricelist!$H$5:$H$123,MATCH(Quote!$B17,Pricelist!$E$5:$E$123,0))) -> 0 | F15: =IF(Quote!$B17="",0,Quote!$F17*INDEX(Pricelist!$I$5:$I$123,MATCH(Quote!$B17,Pricelist!$E$5:$E$123,0))) -> 0 | G15: =IF(Quote!$B17="",0,Quote!$F17*INDEX(Pricelist!$J$5:$J$123,MATCH(Quote!$B17,Pricelist!$E$5:$E$123,0))) -> 0 | H15: =IF(Quote!$B17="",0,Quote!$F17*INDEX(Pricelist!$K$5:$K$123,MATCH(Quote!$B17,Pricelist!$E$5:$E$123,0))) -> 0 | I15: =IF(Quote!$B17="",0,Quote!$F17*INDEX(Pricelist!$L$5:$L$123,MATCH(Quote!$B17,Pricelist!$E$5:$E$123,0))) -> 0 | J15: =IF(Quote!$B17="",0,Quote!$F17*INDEX(Pricelist!$M$5:$M$123,MATCH(Quote!$B17,Pricelist!$E$5:$E$123,0))) -> 0 | K15: =IF(Quote!$B17="",0,Quote!$F17*INDEX(Pricelist!$N$5:$N$123,MATCH(Quote!$B17,Pricelist!$E$5:$E$123,0))) -> 0
A16: 11 | B16: =Quote!B18 -> 0 | C16: =IF(Quote!B18="","",Quote!F18) | D16: =IF(Quote!$B18="",0,Quote!$F18*INDEX(Pricelist!$G$5:$G$123,MATCH(Quote!$B18,Pricelist!$E$5:$E$123,0))) -> 0 | E16: =IF(Quote!$B18="",0,Quote!$F18*INDEX(Pricelist!$H$5:$H$123,MATCH(Quote!$B18,Pricelist!$E$5:$E$123,0))) -> 0 | F16: =IF(Quote!$B18="",0,Quote!$F18*INDEX(Pricelist!$I$5:$I$123,MATCH(Quote!$B18,Pricelist!$E$5:$E$123,0))) -> 0 | G16: =IF(Quote!$B18="",0,Quote!$F18*INDEX(Pricelist!$J$5:$J$123,MATCH(Quote!$B18,Pricelist!$E$5:$E$123,0))) -> 0 | H16: =IF(Quote!$B18="",0,Quote!$F18*INDEX(Pricelist!$K$5:$K$123,MATCH(Quote!$B18,Pricelist!$E$5:$E$123,0))) -> 0 | I16: =IF(Quote!$B18="",0,Quote!$F18*INDEX(Pricelist!$L$5:$L$123,MATCH(Quote!$B18,Pricelist!$E$5:$E$123,0))) -> 0 | J16: =IF(Quote!$B18="",0,Quote!$F18*INDEX(Pricelist!$M$5:$M$123,MATCH(Quote!$B18,Pricelist!$E$5:$E$123,0))) -> 0 | K16: =IF(Quote!$B18="",0,Quote!$F18*INDEX(Pricelist!$N$5:$N$123,MATCH(Quote!$B18,Pricelist!$E$5:$E$123,0))) -> 0
A17: 12 | B17: =Quote!B19 -> 0 | C17: =IF(Quote!B19="","",Quote!F19) | D17: =IF(Quote!$B19="",0,Quote!$F19*INDEX(Pricelist!$G$5:$G$123,MATCH(Quote!$B19,Pricelist!$E$5:$E$123,0))) -> 0 | E17: =IF(Quote!$B19="",0,Quote!$F19*INDEX(Pricelist!$H$5:$H$123,MATCH(Quote!$B19,Pricelist!$E$5:$E$123,0))) -> 0 | F17: =IF(Quote!$B19="",0,Quote!$F19*INDEX(Pricelist!$I$5:$I$123,MATCH(Quote!$B19,Pricelist!$E$5:$E$123,0))) -> 0 | G17: =IF(Quote!$B19="",0,Quote!$F19*INDEX(Pricelist!$J$5:$J$123,MATCH(Quote!$B19,Pricelist!$E$5:$E$123,0))) -> 0 | H17: =IF(Quote!$B19="",0,Quote!$F19*INDEX(Pricelist!$K$5:$K$123,MATCH(Quote!$B19,Pricelist!$E$5:$E$123,0))) -> 0 | I17: =IF(Quote!$B19="",0,Quote!$F19*INDEX(Pricelist!$L$5:$L$123,MATCH(Quote!$B19,Pricelist!$E$5:$E$123,0))) -> 0 | J17: =IF(Quote!$B19="",0,Quote!$F19*INDEX(Pricelist!$M$5:$M$123,MATCH(Quote!$B19,Pricelist!$E$5:$E$123,0))) -> 0 | K17: =IF(Quote!$B19="",0,Quote!$F19*INDEX(Pricelist!$N$5:$N$123,MATCH(Quote!$B19,Pricelist!$E$5:$E$123,0))) -> 0
... A35: 30 | B35: =Quote!B37 -> 0 | C35: =IF(Quote!B37="","",Quote!F37) | D35: =IF(Quote!$B37="",0,Quote!$F37*INDEX(Pricelist!$G$5:$G$123,MATCH(Quote!$B37,Pricelist!$E$5:$E$123,0))) -> 0 | E35: =IF(Quote!$B37="",0,Quote!$F37*INDEX(Pricelist!$H$5:$H$123,MATCH(Quote!$B37,Pricelist!$E$5:$E$123,0))) -> 0 | F35: =IF(Quote!$B37="",0,Quote!$F37*INDEX(Pricelist!$I$5:$I$123,MATCH(Quote!$B37,Pricelist!$E$5:$E$123,0))) -> 0 | G35: =IF(Quote!$B37="",0,Quote!$F37*INDEX(Pricelist!$J$5:$J$123,MATCH(Quote!$B37,Pricelist!$E$5:$E$123,0))) -> 0 | H35: =IF(Quote!$B37="",0,Quote!$F37*INDEX(Pricelist!$K$5:$K$123,MATCH(Quote!$B37,Pricelist!$E$5:$E$123,0))) -> 0 | I35: =IF(Quote!$B37="",0,Quote!$F37*INDEX(Pricelist!$L$5:$L$123,MATCH(Quote!$B37,Pricelist!$E$5:$E$123,0))) -> 0 | J35: =IF(Quote!$B37="",0,Quote!$F37*INDEX(Pricelist!$M$5:$M$123,MATCH(Quote!$B37,Pricelist!$E$5:$E$123,0))) -> 0 | K35: =IF(Quote!$B37="",0,Quote!$F37*INDEX(Pricelist!$N$5:$N$123,MATCH(Quote!$B37,Pricelist!$E$5:$E$123,0))) -> 0
B36: Monthly buy cost of this quote (USD) | D36: =SUM(D6:D35) -> 907 | E36: =SUM(E6:E35) -> 850.31 | F36: =SUM(F6:F35) -> 788.14 | G36: =SUM(G6:G35) -> 707.66 | H36: =SUM(H6:H35) -> 652.12 | I36: =SUM(I6:I35) -> 623.73 | J36: =SUM(J6:J35) -> 596.76 | K36: =SUM(K6:K35) -> 584.56
B37: Saving versus selected tier (USD per month) | D37: =INDEX($D$36:$K$36,1,MATCH(Inputs!$B$16,$D$5:$K$5,0))-D36 -> -118.86 | E37: =INDEX($D$36:$K$36,1,MATCH(Inputs!$B$16,$D$5:$K$5,0))-E36 -> -62.17 | F37: =INDEX($D$36:$K$36,1,MATCH(Inputs!$B$16,$D$5:$K$5,0))-F36 -> 0 | G37: =INDEX($D$36:$K$36,1,MATCH(Inputs!$B$16,$D$5:$K$5,0))-G36 -> 80.48 | H37: =INDEX($D$36:$K$36,1,MATCH(Inputs!$B$16,$D$5:$K$5,0))-H36 -> 136.02 | I37: =INDEX($D$36:$K$36,1,MATCH(Inputs!$B$16,$D$5:$K$5,0))-I36 -> 164.41 | J37: =INDEX($D$36:$K$36,1,MATCH(Inputs!$B$16,$D$5:$K$5,0))-J36 -> 191.38 | K37: =INDEX($D$36:$K$36,1,MATCH(Inputs!$B$16,$D$5:$K$5,0))-K36 -> 203.58
B38: Saving versus selected tier (%) | D38: =IF(INDEX($D$36:$K$36,1,MATCH(Inputs!$B$16,$D$5:$K$5,0))=0,0,D37/INDEX($D$36:$K$36,1,MATCH(Inputs!$B$16,$D$5:$K$5,0))) -> -0.15081077 | E38: =IF(INDEX($D$36:$K$36,1,MATCH(Inputs!$B$16,$D$5:$K$5,0))=0,0,E37/INDEX($D$36:$K$36,1,MATCH(Inputs!$B$16,$D$5:$K$5,0))) -> -0.078881925 | F38: =IF(INDEX($D$36:$K$36,1,MATCH(Inputs!$B$16,$D$5:$K$5,0))=0,0,F37/INDEX($D$36:$K$36,1,MATCH(Inputs!$B$16,$D$5:$K$5,0))) -> 0 | G38: =IF(INDEX($D$36:$K$36,1,MATCH(Inputs!$B$16,$D$5:$K$5,0))=0,0,G37/INDEX($D$36:$K$36,1,MATCH(Inputs!$B$16,$D$5:$K$5,0))) -> 0.10211384 | H38: =IF(INDEX($D$36:$K$36,1,MATCH(Inputs!$B$16,$D$5:$K$5,0))=0,0,H37/INDEX($D$36:$K$36,1,MATCH(Inputs!$B$16,$D$5:$K$5,0))) -> 0.17258355 | I38: =IF(INDEX($D$36:$K$36,1,MATCH(Inputs!$B$16,$D$5:$K$5,0))=0,0,I37/INDEX($D$36:$K$36,1,MATCH(Inputs!$B$16,$D$5:$K$5,0))) -> 0.20860507 | J38: =IF(INDEX($D$36:$K$36,1,MATCH(Inputs!$B$16,$D$5:$K$5,0))=0,0,J37/INDEX($D$36:$K$36,1,MATCH(Inputs!$B$16,$D$5:$K$5,0))) -> 0.24282488 | K38: =IF(INDEX($D$36:$K$36,1,MATCH(Inputs!$B$16,$D$5:$K$5,0))=0,0,K37/INDEX($D$36:$K$36,1,MATCH(Inputs!$B$16,$D$5:$K$5,0))) -> 0.25830436
B39: Selected tier? | D39: =IF(D5=Inputs!$B$16,"selected","") | E39: =IF(E5=Inputs!$B$16,"selected","") | F39: =IF(F5=Inputs!$B$16,"selected","") -> selected | G39: =IF(G5=Inputs!$B$16,"selected","") | H39: =IF(H5=Inputs!$B$16,"selected","") | I39: =IF(I5=Inputs!$B$16,"selected","") | J39: =IF(J5=Inputs!$B$16,"selected","") | K39: =IF(K5=Inputs!$B$16,"selected","")

Sheet Summary
A1: Commercial summary — for the proposal
A2: ="Prepared for "&Inputs!B10&" · Reference "&Inputs!B11&" · "&Inputs!B12 -> Prepared for Example Trading Co. (illustrative) · Reference NS-ACR-2026-001 · 2026-10-01
A3: ="Currency "&Inputs!B13&" · USD reference rate "&TEXT(Inputs!B14,"0.0000")&" · VAT "&TEXT(Inputs!B15,"0%")&" shown separately · Valid "&Inputs!B18&" days" -> Currency SAR · USD reference rate 3.7500 · VAT 15% shown separately · Valid 90 days
A5: Line | B5: Quantity | C5: Unit price per month | D5: Monthly total
A6: =IF(Quote!B8="","",Quote!B8) -> Ultimate Protection - WL - Server (3 TB of Acronis Hosted Storage included) - G2 - Acronis Cyber Protect Cloud | B6: =IF(Quote!B8="","",Quote!F8) -> 2 | C6: =IF(Quote!B8="","",Quote!M8) -> 431.94 | D6: =IF(Quote!B8="","",Quote!O8) -> 863.88
A7: =IF(Quote!B9="","",Quote!B9) -> Ultimate Protection - WL - Workstation (300 GB of Acronis Hosted Storage included) - G2 - Acronis Cyber Protect Cloud | B7: =IF(Quote!B9="","",Quote!F9) -> 25 | C7: =IF(Quote!B9="","",Quote!M9) -> 79.96 | D7: =IF(Quote!B9="","",Quote!O9) -> 1999
A8: =IF(Quote!B10="","",Quote!B10) -> Ultimate Protection - WL - Microsoft 365 seat (unlimited Acronis Hosted Cloud Storage included1) - G2 - Acronis Cyber Protect Cloud | B8: =IF(Quote!B10="","",Quote!F10) -> 30 | C8: =IF(Quote!B10="","",Quote!M10) -> 48.98 | D8: =IF(Quote!B10="","",Quote!O10) -> 1469.4
A9: =IF(Quote!B11="","",Quote!B11) -> Solution-based Licensing - Security Awareness Training (per user) - Acronis Cyber Protect Cloud | B9: =IF(Quote!B11="","",Quote!F11) -> 30 | C9: =IF(Quote!B11="","",Quote!M11) -> 7.15 | D9: =IF(Quote!B11="","",Quote!O11) -> 214.5
A10: =IF(Quote!B12="","",Quote!B12) | B10: =IF(Quote!B12="","",Quote!F12) | C10: =IF(Quote!B12="","",Quote!M12) | D10: =IF(Quote!B12="","",Quote!O12)
A11: =IF(Quote!B13="","",Quote!B13) | B11: =IF(Quote!B13="","",Quote!F13) | C11: =IF(Quote!B13="","",Quote!M13) | D11: =IF(Quote!B13="","",Quote!O13)
A12: =IF(Quote!B14="","",Quote!B14) | B12: =IF(Quote!B14="","",Quote!F14) | C12: =IF(Quote!B14="","",Quote!M14) | D12: =IF(Quote!B14="","",Quote!O14)
A13: =IF(Quote!B15="","",Quote!B15) | B13: =IF(Quote!B15="","",Quote!F15) | C13: =IF(Quote!B15="","",Quote!M15) | D13: =IF(Quote!B15="","",Quote!O15)
A14: =IF(Quote!B16="","",Quote!B16) | B14: =IF(Quote!B16="","",Quote!F16) | C14: =IF(Quote!B16="","",Quote!M16) | D14: =IF(Quote!B16="","",Quote!O16)
A15: =IF(Quote!B17="","",Quote!B17) | B15: =IF(Quote!B17="","",Quote!F17) | C15: =IF(Quote!B17="","",Quote!M17) | D15: =IF(Quote!B17="","",Quote!O17)
A16: =IF(Quote!B18="","",Quote!B18) | B16: =IF(Quote!B18="","",Quote!F18) | C16: =IF(Quote!B18="","",Quote!M18) | D16: =IF(Quote!B18="","",Quote!O18)
A17: =IF(Quote!B19="","",Quote!B19) | B17: =IF(Quote!B19="","",Quote!F19) | C17: =IF(Quote!B19="","",Quote!M19) | D17: =IF(Quote!B19="","",Quote!O19)
... A35: =IF(Quote!B37="","",Quote!B37) | B35: =IF(Quote!B37="","",Quote!F37) | C35: =IF(Quote!B37="","",Quote!M37) | D35: =IF(Quote!B37="","",Quote!O37)
A36: Managed service: operations, monitoring, restore tests, monthly report | B36: =Quote!B43 -> 87 | C36: =IF(Quote!B43=0,0,Quote!B44/Quote!B43) -> 15 | D36: =Quote!B44 -> 1305
A37: Monthly subtotal excluding VAT | D37: =Quote!B45 -> 5851.78
A38: VAT | D38: =Quote!B46 -> 877.767
A39: Monthly total including VAT | D39: =Quote!B47 -> 6729.547
A40: Annual equivalent excluding VAT | D40: =Quote!B48 -> 70221.36
A41: One-time services excluding VAT | D41: =Quote!B50 -> 7500
A43: Prices are per unit per month in the stated currency, billed monthly in advance, quantities reconciled quarterly, storage beyond included quotas billed per GB per month as listed.

Sheet Data centers
A1: Acronis data centers and storage groups (from the calculator)
A3: Group | B3: Country | C3: Data center | D3: Geo-redundancy | E3: Cyber Employee | F3: Cyber Frame Cloud
A4: G1 | B4: USA | C4: Phoenix | D4: Yes | E4: Yes | F4: Yes
A5: G1 | B5: USA | C5: Ashburn | D5: Yes | E5: Yes | F5: Yes
A6: G1 | B6: Germany | C6: Frankfurt | D6: Yes | F6: Yes
A7: G1 | B7: Switzerland | C7: Lupfig | F7: Yes
A8: G1 | B8: UK | C8: London | D8: Yes | E8: Yes | F8: Yes
A9: G1 | B9: Japan | C9: Nagano | F9: Yes
A10: G1 | B10: Japan | C10: Kanagawa
A11: G1 | B11: Germany | C11: Cologne | D11: Yes | F11: Yes
A12: G1 | B12: France | C12: Strasbourg | F12: Yes
A13: G1 | B13: USA | C13: St.Louis | E13: Yes
A14: G1 | B14: Singapore | C14: Singapore | F14: Yes
A15: G1 | B15: Australia | C15: Sydney | E15: Yes | F15: Yes
A16: G1 | B16: Canada | C16: Vancouver | D16: Yes | E16: Yes | F16: Yes
A17: G1 | B17: Canada | C17: Toronto | D17: Yes | E17: Yes | F17: Yes
A18: G1 | B18: New Zealand | C18: Auckland | F18: Yes
A19: G1 | B19: Liechtenstein | C19: Balzers
A20: G1 | B20: Indonesia | C20: Jakarta | F20: Yes
A21: G1 | B21: India | C21: Mumbai | F21: Yes
A22: G1 | B22: Spain | C22: Valencia | F22: Yes
A23: G1 | B23: Israel | C23: Tel Aviv | F23: Yes
A24: G1 | B24: Portugal | C24: Lisbon | F24: Yes
A25: G1 | B25: Korea | C25: Seoul | F25: Yes
A26: G1 | B26: Czech Republic | C26: Prague | F26: Yes
A27: G1 | B27: Greece | C27: Thessaloniki | F27: Yes
A28: G1 | B28: Brazil | C28: Sao Paulo | D28: Yes | F28: Yes
A29: G1 | B29: Poland | C29: Warsaw | F29: Yes
A30: G1 | B30: Austria | C30: Vienna | F30: Yes
A31: G1 | B31: Denmark | C31: Billund | F31: Yes
A32: G1 | B32: Bulgaria | C32: Sofia | F32: Yes
A33: G1 | B33: Turkey | C33: Istanbul | F33: Yes
A34: G1 | B34: Norway | C34: Oslo | F34: Yes
A35: G1 | B35: Finland | C35: Helsinki | F35: Yes
A36: G1 | B36: Italy | C36: Rome | F36: Yes
A37: G1 | B37: Sweden | C37: Goteborg | F37: Yes
A38: G1 | B38: Mexico | C38: Mexico City | F38: Yes
A39: G1 | B39: Malaysia | C39: Kuala Lumpur | F39: Yes
A40: G2 | B40: South Africa | C40: Johannesburg | F40: Yes
... A42: G2 | B42: Taiwan | C42: Taipei | F42: Yes
